LICENSE
MANIFEST.in
README.rst
setup.py
src/django_language_flags.egg-info/PKG-INFO
src/django_language_flags.egg-info/SOURCES.txt
src/django_language_flags.egg-info/dependency_links.txt
src/django_language_flags.egg-info/top_level.txt
src/language_flags/__init__.py
src/language_flags/static/css/flags.css
src/language_flags/static/css/flags.min.css
src/language_flags/static/img/blank.png
src/language_flags/static/img/flags.png
src/language_flags/templates/language_flags/flagrow.html
src/language_flags/templatetags/__init__.py
src/language_flags/templatetags/language_flags_tags.py